{
  "version": "7",
  "dialect": "postgresql",
  "entries": [
    {
      "idx": 0,
      "version": "7",
      "when": 1722630253017,
      "tag": "0000_spooky_king_bedlam",
      "breakpoints": true
    },
    {
      "idx": 1,
      "version": "7",
      "when": 1722653568631,
      "tag": "0001_chief_emma_frost",
      "breakpoints": true
    },
    {
      "idx": 2,
      "version": "7",
      "when": 1722654315369,
      "tag": "0002_safe_rattler",
      "breakpoints": true
    },
    {
      "idx": 3,
      "version": "7",
      "when": 1722654485941,
      "tag": "0003_wealthy_iron_patriot",
      "breakpoints": true
    },
    {
      "idx": 4,
      "version": "7",
      "when": 1722658436250,
      "tag": "0004_uneven_justin_hammer",
      "breakpoints": true
    },
    {
      "idx": 5,
      "version": "7",
      "when": 1722665198633,
      "tag": "0005_windy_ironclad",
      "breakpoints": true
    },
    {
      "idx": 6,
      "version": "7",
      "when": 1722669003424,
      "tag": "0006_quick_catseye",
      "breakpoints": true
    },
    {
      "idx": 7,
      "version": "7",
      "when": 1722688361331,
      "tag": "0007_dear_mariko_yashida",
      "breakpoints": true
    },
    {
      "idx": 8,
      "version": "7",
      "when": 1722688764867,
      "tag": "0008_redundant_hellcat",
      "breakpoints": true
    },
    {
      "idx": 9,
      "version": "7",
      "when": 1722705385453,
      "tag": "0009_boring_omega_sentinel",
      "breakpoints": true
    },
    {
      "idx": 10,
      "version": "7",
      "when": 1722707819287,
      "tag": "0010_dark_warbound",
      "breakpoints": true
    },
    {
      "idx": 11,
      "version": "7",
      "when": 1722714421901,
      "tag": "0011_absent_brother_voodoo",
      "breakpoints": true
    }
  ]
}